{
    "rpcFunctions": [
        {
            "name": "isSjaak",
            "parameters": [
                {
                    "index": 0,
                    "name": "a",
                    "value": {
                        "type": "string"
                    }
                }
            ],
            "returnType": {
                "type": "boolean"
            },
            "modelIds": []
        },
        {
            "name": "add",
            "parameters": [
                {
                    "index": 0,
                    "name": "a",
                    "value": {
                        "type": "number"
                    }
                },
                {
                    "index": 1,
                    "name": "b",
                    "value": {
                        "type": "number"
                    }
                }
            ],
            "returnType": {
                "type": "number"
            },
            "modelIds": []
        }
    ],
    "models": {},
    "refs": {}
}